[
  {
    "name": "Paris",
    "longitude": 2.3522,
    "latitude": 48.8566,
    "population": 2148000,
    "average_airfare_price_usd": 800,
    "average_hotel_price_usd": 200,
    "top_5_things_to_do": [
      "Visit the Eiffel Tower",
      "Explore the Louvre Museum",
      "Stroll along the Seine River",
      "Climb the steps to Sacré-Cœur Basilica",
      "Discover Montmartre neighborhood"
    ]
  },
  {
    "name": "Tokyo",
    "longitude": 139.6917,
    "latitude": 35.6895,
    "population": 13929286,
    "average_airfare_price_usd": 1000,
    "average_hotel_price_usd": 150,
    "top_5_things_to_do": [
      "Visit the historic Senso-ji Temple",
      "Explore the bustling streets of Shibuya",
      "Experience traditional tea ceremony",
      "Discover the beauty of Meiji Shrine",
      "Enjoy the panoramic view from Tokyo Tower"
    ]
  },
  {
    "name": "New York City",
    "longitude": -74.006,
    "latitude": 40.7128,
    "population": 8398748,
    "average_airfare_price_usd": 700,
    "average_hotel_price_usd": 250,
    "top_5_things_to_do": [
      "Walk through Central Park",
      "Visit the Statue of Liberty",
      "Explore Times Square",
      "Experience the views from the Empire State Building",
      "Enjoy Broadway shows"
    ]
  },
  {
    "name": "London",
    "longitude": -0.1276,
    "latitude": 51.5074,
    "population": 9304016,
    "average_airfare_price_usd": 900,
    "average_hotel_price_usd": 180,
    "top_5_things_to_do": [
      "Visit the British Museum",
      "Explore the Tower of London",
      "Take a ride on the London Eye",
      "Stroll through Hyde Park",
      "Discover the nightlife in Soho"
    ]
  },
  {
    "name": "Rome",
    "longitude": 12.4964,
    "latitude": 41.9028,
    "population": 2872800,
    "average_airfare_price_usd": 850,
    "average_hotel_price_usd": 170,
    "top_5_things_to_do": [
      "Visit the Colosseum",
      "Explore Vatican City and St. Peter's Basilica",
      "Throw a coin in the Trevi Fountain",
      "Discover the Roman Forum",
      "Indulge in Italian cuisine in Trastevere"
    ]
  },
  {
    "name": "Bangkok",
    "longitude": 100.5018,
    "latitude": 13.7563,
    "population": 8280925,
    "average_airfare_price_usd": 600,
    "average_hotel_price_usd": 80,
    "top_5_things_to_do": [
      "Explore the Grand Palace",
      "Visit Wat Arun",
      "Take a boat ride along the Chao Phraya River",
      "Shop at Chatuchak Weekend Market",
      "Experience vibrant nightlife in Khao San Road"
    ]
  },
  {
    "name": "Istanbul",
    "longitude": 28.9784,
    "latitude": 41.0082,
    "population": 15460000,
    "average_airfare_price_usd": 750,
    "average_hotel_price_usd": 120,
    "top_5_things_to_do": [
      "Explore the Hagia Sophia",
      "Visit the Blue Mosque",
      "Discover Topkapi Palace",
      "Shop at the Grand Bazaar",
      "Take a cruise on the Bosphorus"
    ]
  },
  {
    "name": "Dubai",
    "longitude": 55.2708,
    "latitude": 25.2048,
    "population": 3137000,
    "average_airfare_price_usd": 900,
    "average_hotel_price_usd": 150,
    "top_5_things_to_do": [
      "Visit the Burj Khalifa",
      "Experience the Dubai Fountain",
      "Explore the Dubai Mall",
      "Take a desert safari",
      "Relax at Jumeirah Beach"
    ]
  },
  {
    "name": "Barcelona",
    "longitude": 2.1734,
    "latitude": 41.3851,
    "population": 1664182,
    "average_airfare_price_usd": 750,
    "average_hotel_price_usd": 160,
    "top_5_things_to_do": [
      "Visit the Sagrada Familia",
      "Explore Park Güell",
      "Stroll along La Rambla",
      "Discover the Gothic Quarter",
      "Relax on the beaches of Barceloneta"
    ]
  },
  {
    "name": "Sydney",
    "longitude": 151.2093,
    "latitude": -33.8688,
    "population": 5312163,
    "average_airfare_price_usd": 1100,
    "average_hotel_price_usd": 200,
    "top_5_things_to_do": [
      "Climb the Sydney Harbour Bridge",
      "Visit the Sydney Opera House",
      "Relax at Bondi Beach",
      "Explore the Royal Botanic Garden",
      "Take a ferry ride to Manly Beach"
    ]
  },
  {
    "name": "Amsterdam",
    "longitude": 4.8952,
    "latitude": 52.3702,
    "population": 860124,
    "average_airfare_price_usd": 800,
    "average_hotel_price_usd": 170,
    "top_5_things_to_do": [
      "Explore the Van Gogh Museum",
      "Take a canal cruise",
      "Visit the Anne Frank House",
      "Discover the Rijksmuseum",
      "Experience the nightlife in the Red Light District"
    ]
  },
  {
    "name": "Los Angeles",
    "longitude": -118.2437,
    "latitude": 34.0522,
    "population": 3990456,
    "average_airfare_price_usd": 650,
    "average_hotel_price_usd": 180,
    "top_5_things_to_do": [
      "Visit the Hollywood Walk of Fame",
      "Explore Universal Studios Hollywood",
      "Relax at Santa Monica Pier",
      "Discover Griffith Observatory",
      "Shop on Rodeo Drive"
    ]
  },
  {
    "name": "Hong Kong",
    "longitude": 114.1694,
    "latitude": 22.3193,
    "population": 7392000,
    "average_airfare_price_usd": 850,
    "average_hotel_price_usd": 140,
    "top_5_things_to_do": [
      "Take the Peak Tram to Victoria Peak",
      "Explore the markets of Mong Kok",
      "Visit Tian Tan Buddha on Lantau Island",
      "Enjoy the nightlife in Lan Kwai Fong",
      "Discover the street food in Temple Street Night Market"
    ]
  },
  {
    "name": "Singapore",
    "longitude": 103.8198,
    "latitude": 1.3521,
    "population": 5704000,
    "average_airfare_price_usd": 900,
    "average_hotel_price_usd": 160,
    "top_5_things_to_do": [
      "Explore Gardens by the Bay",
      "Visit Marina Bay Sands",
      "Discover Sentosa Island",
      "Explore Chinatown",
      "Experience the Singapore Zoo"
    ]
  },
  {
    "name": "Venice",
    "longitude": 12.3155,
    "latitude": 45.4408,
    "population": 261905,
    "average_airfare_price_usd": 850,
    "average_hotel_price_usd": 200,
    "top_5_things_to_do": [
      "Take a gondola ride along the canals",
      "Explore St. Mark's Basilica",
      "Visit Doge's Palace",
      "Discover the Rialto Bridge",
      "Enjoy the atmosphere of Piazza San Marco"
    ]
  },
  {
    "name": "San Francisco",
    "longitude": -122.4194,
    "latitude": 37.7749,
    "population": 884363,
    "average_airfare_price_usd": 700,
    "average_hotel_price_usd": 220,
    "top_5_things_to_do": [
      "Walk across the Golden Gate Bridge",
      "Visit Alcatraz Island",
      "Explore Fisherman's Wharf",
      "Ride a cable car",
      "Discover Golden Gate Park"
    ]
  },
  {
    "name": "Vienna",
    "longitude": 16.3738,
    "latitude": 48.2082,
    "population": 1911728,
    "average_airfare_price_usd": 800,
    "average_hotel_price_usd": 150,
    "top_5_things_to_do": [
      "Visit Schönbrunn Palace",
      "Explore Belvedere Palace",
      "Discover St. Stephen's Cathedral",
      "Enjoy a performance at the Vienna State Opera",
      "Take a stroll through the historic city center"
    ]
  },
  {
    "name": "Las Vegas",
    "longitude": -115.1398,
    "latitude": 36.1699,
    "population": 651319,
    "average_airfare_price_usd": 500,
    "average_hotel_price_usd": 120,
    "top_5_things_to_do": [
      "Experience the Las Vegas Strip",
      "Visit iconic hotels and casinos",
      "Watch a spectacular show",
      "Explore Fremont Street",
      "Take a helicopter tour of the Grand Canyon"
    ]
  },
  {
    "name": "Florence",
    "longitude": 11.2558,
    "latitude": 43.7696,
    "population": 383083,
    "average_airfare_price_usd": 850,
    "average_hotel_price_usd": 180,
    "top_5_things_to_do": [
      "Visit the Uffizi Gallery",
      "Explore the Florence Cathedral (Duomo)",
      "Discover the Ponte Vecchio",
      "Stroll through Piazza della Signoria",
      "Experience the beauty of Boboli Gardens"
    ]
  },
  {
    "name": "Marrakech",
    "longitude": -7.5898,
    "latitude": 31.6295,
    "population": 1062000,
    "average_airfare_price_usd": 600,
    "average_hotel_price_usd": 80,
    "top_5_things_to_do": [
      "Explore Jardin Majorelle",
      "Discover the bustling Medina",
      "Visit Bahia Palace",
      "Experience Jemaa el-Fnaa square",
      "Relax in a traditional hammam"
    ]
  },
  {
    "name": "Prague",
    "longitude": 14.4378,
    "latitude": 50.0755,
    "population": 1309000,
    "average_airfare_price_usd": 750,
    "average_hotel_price_usd": 130,
    "top_5_things_to_do": [
      "Explore Prague Castle",
      "Visit Charles Bridge",
      "Discover Old Town Square",
      "Enjoy the view from Petřín Hill",
      "Experience Czech cuisine and beer"
    ]
  },
  {
    "name": "Budapest",
    "longitude": 19.0402,
    "latitude": 47.4979,
    "population": 1752286,
    "average_airfare_price_usd": 700,
    "average_hotel_price_usd": 120,
    "top_5_things_to_do": [
      "Relax in the Széchenyi Thermal Bath",
      "Visit Buda Castle",
      "Take a cruise on the Danube River",
      "Discover Fisherman's Bastion",
      "Explore the Great Market Hall"
    ]
  },
  {
    "name": "Seoul",
    "longitude": 126.978,
    "latitude": 37.5665,
    "population": 9720846,
    "average_airfare_price_usd": 800,
    "average_hotel_price_usd": 100,
    "top_5_things_to_do": [
      "Explore Gyeongbokgung Palace",
      "Visit Bukchon Hanok Village",
      "Discover Myeongdong shopping district",
      "Hike up Namsan Mountain",
      "Experience traditional Korean cuisine"
    ]
  },
  {
    "name": "Cairo",
    "longitude": 31.2357,
    "latitude": 30.0444,
    "population": 20484900,
    "average_airfare_price_usd": 600,
    "average_hotel_price_usd": 70,
    "top_5_things_to_do": [
      "Visit the Pyramids of Giza",
      "Explore the Egyptian Museum",
      "Discover Khan el-Khalili market",
      "Explore the Citadel of Cairo",
      "Sail on a felucca along the Nile River"
    ]
  },
  {
    "name": "Mexico City",
    "longitude": -99.1332,
    "latitude": 19.4326,
    "population": 8918653,
    "average_airfare_price_usd": 600,
    "average_hotel_price_usd": 80,
    "top_5_things_to_do": [
      "Visit the National Museum of Anthropology",
      "Explore the historic center (Zocalo)",
      "Discover the Templo Mayor",
      "Visit Chapultepec Park",
      "Explore Frida Kahlo Museum (Casa Azul)"
    ]
  },
  {
    "name": "Berlin",
    "longitude": 13.405,
    "latitude": 52.52,
    "population": 3644826,
    "average_airfare_price_usd": 800,
    "average_hotel_price_usd": 130,
    "top_5_things_to_do": [
      "Visit the Berlin Wall",
      "Explore Brandenburg Gate",
      "Discover Museum Island",
      "Visit the Reichstag building",
      "Experience the nightlife in Kreuzberg"
    ]
  },
  {
    "name": "Rio de Janeiro",
    "longitude": -43.1729,
    "latitude": -22.9068,
    "population": 6718903,
    "average_airfare_price_usd": 900,
    "average_hotel_price_usd": 110,
    "top_5_things_to_do": [
      "Visit Christ the Redeemer",
      "Relax on Copacabana Beach",
      "Explore Sugarloaf Mountain",
      "Discover the Selarón Steps",
      "Experience Rio's vibrant carnival"
    ]
  },
  {
    "name": "Buenos Aires",
    "longitude": -58.3816,
    "latitude": -34.6037,
    "population": 2891082,
    "average_airfare_price_usd": 800,
    "average_hotel_price_usd": 90,
    "top_5_things_to_do": [
      "Explore La Boca neighborhood",
      "Visit Teatro Colón",
      "Discover Recoleta Cemetery",
      "Experience tango in San Telmo",
      "Relax in Palermo Woods"
    ]
  },
  {
    "name": "Cape Town",
    "longitude": 18.4241,
    "latitude": -33.9249,
    "population": 433688,
    "average_airfare_price_usd": 1000,
    "average_hotel_price_usd": 120,
    "top_5_things_to_do": [
      "Visit Table Mountain",
      "Explore Robben Island",
      "Discover Victoria & Alfred Waterfront",
      "Experience Cape of Good Hope",
      "Visit Kirstenbosch National Botanical Garden"
    ]
  },
  {
    "name": "Agra",
    "longitude": 78.0421,
    "latitude": 27.1767,
    "population": 1585704,
    "average_airfare_price_usd": 600,
    "average_hotel_price_usd": 70,
    "top_5_things_to_do": [
      "Visit the Taj Mahal",
      "Discover Agra Fort",
      "Explore Fatehpur Sikri",
      "Visit Tomb of Itimad-ud-Daulah",
      "Experience the sunset at Mehtab Bagh"
    ]
  },
  {
    "name": "Edinburgh",
    "longitude": -3.1883,
    "latitude": 55.9533,
    "population": 537984,
    "average_airfare_price_usd": 800,
    "average_hotel_price_usd": 130,
    "top_5_things_to_do": [
      "Visit Edinburgh Castle",
      "Explore the Royal Mile",
      "Discover Holyrood Palace",
      "Hike up Arthur's Seat",
      "Experience the Edinburgh Festival"
    ]
  },
  {
    "name": "Dublin",
    "longitude": -6.2603,
    "latitude": 53.3498,
    "population": 1173179,
    "average_airfare_price_usd": 700,
    "average_hotel_price_usd": 120,
    "top_5_things_to_do": [
      "Visit Trinity College and the Book of Kells",
      "Explore Guinness Storehouse",
      "Discover Dublin Castle",
      "Stroll through Temple Bar",
      "Take a walk in Phoenix Park"
    ]
  },
  {
    "name": "Hanoi",
    "longitude": 105.8342,
    "latitude": 21.0285,
    "population": 7784485,
    "average_airfare_price_usd": 700,
    "average_hotel_price_usd": 80,
    "top_5_things_to_do": [
      "Explore the Old Quarter",
      "Visit Hoan Kiem Lake",
      "Discover Ho Chi Minh Mausoleum",
      "Experience a water puppet show",
      "Indulge in street food"
    ]
  },
  {
    "name": "Santorini",
    "longitude": 25.4284,
    "latitude": 36.3932,
    "population": 15367,
    "average_airfare_price_usd": 1200,
    "average_hotel_price_usd": 300,
    "top_5_things_to_do": [
      "Watch the sunset in Oia",
      "Explore the village of Fira",
      "Visit the ancient city of Akrotiri",
      "Relax on the beaches of Perissa and Kamari",
      "Taste the local wines"
    ]
  },
  {
    "name": "Kyoto",
    "longitude": 135.7681,
    "latitude": 35.0116,
    "population": 1474570,
    "average_airfare_price_usd": 1000,
    "average_hotel_price_usd": 150,
    "top_5_things_to_do": [
      "Visit Kinkaku-ji (Golden Pavilion)",
      "Explore Fushimi Inari Shrine",
      "Discover Arashiyama Bamboo Grove",
      "Visit Kiyomizu-dera Temple",
      "Experience a traditional tea ceremony"
    ]
  },
  {
    "name": "Cusco",
    "longitude": -71.9784,
    "latitude": -13.5319,
    "population": 428450,
    "average_airfare_price_usd": 700,
    "average_hotel_price_usd": 100,
    "top_5_things_to_do": [
      "Explore Machu Picchu",
      "Discover the Sacred Valley",
      "Visit Sacsayhuamán",
      "Explore Plaza de Armas",
      "Experience Inca Trail"
    ]
  },
  {
    "name": "Reykjavik",
    "longitude": -21.9426,
    "latitude": 64.1466,
    "population": 131136,
    "average_airfare_price_usd": 900,
    "average_hotel_price_usd": 180,
    "top_5_things_to_do": [
      "Relax in the Blue Lagoon",
      "Explore the Golden Circle",
      "Discover Hallgrímskirkja Church",
      "Visit Harpa Concert Hall",
      "Experience the Northern Lights"
    ]
  },
  {
    "name": "Helsinki",
    "longitude": 24.9384,
    "latitude": 60.1695,
    "population": 655281,
    "average_airfare_price_usd": 800,
    "average_hotel_price_usd": 150,
    "top_5_things_to_do": [
      "Visit Suomenlinna Fortress",
      "Explore Helsinki Cathedral",
      "Discover Temppeliaukio Church",
      "Experience the Design District",
      "Take a sauna"
    ]
  },
  {
    "name": "Krakow",
    "longitude": 19.9449,
    "latitude": 50.0647,
    "population": 779115,
    "average_airfare_price_usd": 750,
    "average_hotel_price_usd": 100,
    "top_5_things_to_do": [
      "Visit Wawel Castle",
      "Explore the Old Town Market Square",
      "Discover Auschwitz-Birkenau Memorial and Museum",
      "Experience the Wieliczka Salt Mine",
      "Relax by the Vistula River"
    ]
  },
  {
    "name": "Vancouver",
    "longitude": -123.1216,
    "latitude": 49.2827,
    "population": 675218,
    "average_airfare_price_usd": 800,
    "average_hotel_price_usd": 180,
    "top_5_things_to_do": [
      "Explore Stanley Park",
      "Visit Granville Island",
      "Discover Capilano Suspension Bridge Park",
      "Stroll through Gastown",
      "Enjoy the views from Vancouver Lookout"
    ]
  },
  {
    "name": "Boston",
    "longitude": -71.0589,
    "latitude": 42.3601,
    "population": 694583,
    "average_airfare_price_usd": 650,
    "average_hotel_price_usd": 200,
    "top_5_things_to_do": [
      "Walk the Freedom Trail",
      "Visit Fenway Park",
      "Explore the Museum of Fine Arts",
      "Take a stroll in Boston Common",
      "Experience the historic neighborhoods like Beacon Hill and Back Bay"
    ]
  },
  {
    "name": "Osaka",
    "longitude": 135.5022,
    "latitude": 34.6937,
    "population": 2595674,
    "average_airfare_price_usd": 900,
    "average_hotel_price_usd": 120,
    "top_5_things_to_do": [
      "Visit Osaka Castle",
      "Explore Dotonbori district",
      "Experience Universal Studios Japan",
      "Discover Shitennoji Temple",
      "Enjoy street food in Kuromon Ichiba Market"
    ]
  },
  {
    "name": "Manila",
    "longitude": 120.9842,
    "latitude": 14.5995,
    "population": 1780148,
    "average_airfare_price_usd": 700,
    "average_hotel_price_usd": 70,
    "top_5_things_to_do": [
      "Visit Intramuros",
      "Explore Rizal Park",
      "Discover Binondo (Chinatown)",
      "Take a walk along Manila Baywalk",
      "Experience nightlife in Makati"
    ]
  },
  {
    "name": "Moscow",
    "longitude": 37.6173,
    "latitude": 55.7558,
    "population": 12615279,
    "average_airfare_price_usd": 800,
    "average_hotel_price_usd": 100,
    "top_5_things_to_do": [
      "Visit the Kremlin and Red Square",
      "Explore St. Basil's Cathedral",
      "Discover the State Tretyakov Gallery",
      "Experience the Moscow Metro stations",
      "Take a stroll along Arbat Street"
    ]
  },
  {
    "name": "Tel Aviv",
    "longitude": 34.7818,
    "latitude": 32.0853,
    "population": 4515000,
    "average_airfare_price_usd": 900,
    "average_hotel_price_usd": 150,
    "top_5_things_to_do": [
      "Relax on the beaches of Tel Aviv",
      "Explore Jaffa's Old City",
      "Visit Carmel Market",
      "Discover the Tel Aviv Museum of Art",
      "Experience the nightlife on Rothschild Boulevard"
    ]
  },
  {
    "name": "Quebec",
    "longitude": -71.208,
    "latitude": 46.8139,
    "population": 531902,
    "average_airfare_price_usd": 700,
    "average_hotel_price_usd": 180,
    "top_5_things_to_do": [
      "Explore Old Quebec (Vieux-Québec)",
      "Visit Château Frontenac",
      "Walk along Dufferin Terrace",
      "Discover Quartier Petit Champlain",
      "Experience Montmorency Falls"
    ]
  },
  {
    "name": "Lisbon",
    "longitude": -9.1393,
    "latitude": 38.7223,
    "population": 505526,
    "average_airfare_price_usd": 800,
    "average_hotel_price_usd": 130,
    "top_5_things_to_do": [
      "Explore Alfama district",
      "Visit Belém Tower",
      "Discover Jerónimos Monastery",
      "Experience the nightlife in Bairro Alto",
      "Relax at Praça do Comércio"
    ]
  },
  {
    "name": "Madrid",
    "longitude": -3.7038,
    "latitude": 40.4168,
    "population": 3223334,
    "average_airfare_price_usd": 750,
    "average_hotel_price_usd": 140,
    "top_5_things_to_do": [
      "Visit the Prado Museum",
      "Explore the Royal Palace of Madrid",
      "Discover Retiro Park",
      "Experience Plaza Mayor",
      "Enjoy tapas in La Latina"
    ]
  },
  {
    "name": "Jakarta",
    "longitude": 106.865,
    "latitude": -6.2088,
    "population": 10187595,
    "average_airfare_price_usd": 600,
    "average_hotel_price_usd": 80,
    "top_5_things_to_do": [
      "Explore the National Monument (Monas)",
      "Visit the Old Town (Kota Tua)",
      "Discover Taman Mini Indonesia Indah",
      "Experience Ancol Dreamland",
      "Indulge in Indonesian cuisine"
    ]
  },
  {
    "name": "Zurich",
    "longitude": 8.5417,
    "latitude": 47.3769,
    "population": 402762,
    "average_airfare_price_usd": 1100,
    "average_hotel_price_usd": 200,
    "top_5_things_to_do": [
      "Explore Old Town (Altstadt)",
      "Visit the Swiss National Museum",
      "Enjoy a boat ride on Lake Zurich",
      "Discover Bahnhofstrasse (shopping street)",
      "Relax in the Botanical Garden"
    ]
  }
]
